MANIFEST.in
README.rst
setup.py
docs/conf.py
docs/index.rst
xbob/__init__.py
xbob.db.replay.egg-info/PKG-INFO
xbob.db.replay.egg-info/SOURCES.txt
xbob.db.replay.egg-info/dependency_links.txt
xbob.db.replay.egg-info/entry_points.txt
xbob.db.replay.egg-info/namespace_packages.txt
xbob.db.replay.egg-info/not-zip-safe
xbob.db.replay.egg-info/requires.txt
xbob.db.replay.egg-info/top_level.txt
xbob/db/__init__.py
xbob/db/replay/__init__.py
xbob/db/replay/checkfiles.py
xbob/db/replay/create.py
xbob/db/replay/db.sql3
xbob/db/replay/driver.py
xbob/db/replay/dumplist.py
xbob/db/replay/models.py
xbob/db/replay/query.py
xbob/db/replay/spoofing.py
xbob/db/replay/test.py